fcopy
