Metadata-Version: 1.1
Name: fcopy
Version: 0.1.1
Summary: A copying utility to keep files updated
Home-page: https://github.com/e2raptor/fcopy
Author: Eduardo Pina Fonseca
Author-email: epinaster@gmail.com
License: MIT
Keywords: file utilities admin filesystem copy sync
Platform: UNKNOWN
Classifier: Development Status :: 4 - Beta
Classifier: Intended Audience :: Developers
Classifier: Intended Audience :: End Users/Desktop
Classifier: Topic :: System :: Systems Administration
Classifier: Topic :: Utilities
Classifier: License :: OSI Approved :: MIT License
Classifier: Programming Language :: Python :: 3
